{"document":{"store":{"shape:ckjqCg1EjOv6ma89HMSiv":{"x":-1136.7169081609768,"y":1074.3893815369458,"rotation":0,"isLocked":false,"opacity":1,"meta":{},"id":"shape:ckjqCg1EjOv6ma89HMSiv","type":"text","props":{"color":"black","size":"xl","w":555.4000244140625,"font":"mono","textAlign":"start","autoSize":true,"scale":1,"richText":{"type":"doc","attrs":{"dir":"auto"},"content":[{"type":"paragraph","attrs":{"dir":"auto"},"content":[{"type":"text","text":"I'm building my house"}]}]}},"parentId":"page:page","index":"aO6ztOrG","typeName":"shape"},"shape:KePW5ASjP6tYVW8D0TJfV":{"x":460.2432421300339,"y":826.0178910925491,"rotation":0,"isLocked":false,"opacity":1,"meta":{},"id":"shape:KePW5ASjP6tYVW8D0TJfV","type":"arrow","props":{"kind":"arc","elbowMidPoint":0.5,"dash":"draw","size":"xl","fill":"none","color":"black","labelColor":"black","bend":0,"start":{"x":0,"y":0},"end":{"x":-190.17795149487432,"y":1.5987211554602254e-14},"arrowheadStart":"none","arrowheadEnd":"arrow","richText":{"type":"doc","content":[{"type":"paragraph"}]},"labelPosition":0.5,"font":"draw","scale":1},"parentId":"page:page","index":"aM27KVHV","typeName":"shape"},"asset:685522482":{"id":"asset:685522482","type":"image","typeName":"asset","props":{"name":"1000015475.png","src":"https://res.cloudinary.com/dfmr3wxuj/image/upload/v1780377169/xubinby89veti1bzcglq.png","w":0,"h":0,"mimeType":"image/png","isAnimated":false,"fileSize":185806},"meta":{}},"shape:W6TZP6OP0Qs3gU0cPyIFP":{"x":-1255.102680631176,"y":1137.245829293512,"rotation":0,"isLocked":false,"opacity":1,"meta":{},"id":"shape:W6TZP6OP0Qs3gU0cPyIFP","type":"image","props":{"w":761.272367017223,"h":468.8356957780828,"assetId":"asset:-1566926773","playing":true,"url":"","crop":{"topLeft":{"x":0.045817335447039816,"y":0.19266776957216689},"bottomRight":{"x":0.9259873812009358,"y":0.9154141499439266}},"flipX":false,"flipY":false,"altText":""},"parentId":"page:page","index":"aP2tg99V","typeName":"shape"},"asset:1191422016":{"id":"asset:1191422016","type":"image","typeName":"asset","props":{"name":"tldrawFile","src":"https://res.cloudinary.com/dfmr3wxuj/image/upload/v1780372006/pjjcr71aecqilbwelox0.png","w":0,"h":0,"mimeType":"image/png","isAnimated":false,"fileSize":1531445},"meta":{}},"user:yDUutpbDxf8eX50pO4LtA":{"name":"","color":"#02B1CC","imageUrl":"","meta":{},"id":"user:yDUutpbDxf8eX50pO4LtA","typeName":"user"},"shape:gKv5b_JAOJanw12Uq92P_":{"x":487.83849034801835,"y":795.2301624631306,"rotation":0,"isLocked":false,"opacity":1,"meta":{},"id":"shape:gKv5b_JAOJanw12Uq92P_","type":"text","props":{"color":"black","size":"xl","w":224.01666259765625,"font":"draw","textAlign":"start","autoSize":true,"scale":1,"richText":{"type":"doc","attrs":{"dir":"auto"},"content":[{"type":"paragraph","attrs":{"dir":"auto"},"content":[{"type":"text","text":"try it out!"}]}]}},"parentId":"page:page","index":"aLff3z0l","typeName":"shape"},"shape:1tDvkiOX39jOEKcH1ZDyM":{"x":-1417.8188007292852,"y":1600.6397591711595,"rotation":0,"isLocked":false,"opacity":1,"meta":{},"id":"shape:1tDvkiOX39jOEKcH1ZDyM","type":"image","props":{"w":494.3410274285622,"h":320.0080165044967,"assetId":"asset:411255295","playing":true,"url":"","crop":{"topLeft":{"x":0,"y":0.09547016847851432},"bottomRight":{"x":0.8829353886513456,"y":0.8575524470320582}},"flipX":false,"flipY":false,"altText":""},"parentId":"page:page","index":"aRHctyKV","typeName":"shape"},"shape:F7I6Du1dzAl40yuEJZMBM":{"x":-426.70430453275367,"y":1453.5347569774679,"rotation":0,"isLocked":false,"opacity":1,"meta":{},"id":"shape:F7I6Du1dzAl40yuEJZMBM","type":"text","props":{"color":"black","size":"m","w":116.19999694824219,"font":"mono","textAlign":"start","autoSize":true,"scale":1,"richText":{"type":"doc","attrs":{"dir":"auto"},"content":[{"type":"paragraph","attrs":{"dir":"auto"},"content":[{"type":"text","text":"(winter)"}]}]}},"parentId":"page:page","index":"aTcygQQV","typeName":"shape"},"shape:mqWxkv0hWAmmZH0H1TU2V":{"x":494.7524701881845,"y":174.19505753067307,"rotation":0,"isLocked":false,"opacity":1,"meta":{},"id":"shape:mqWxkv0hWAmmZH0H1TU2V","type":"image","props":{"w":799.8308695037888,"h":329.8603873812783,"assetId":"asset:-1018698235","playing":true,"url":"","crop":{"topLeft":{"x":0,"y":0.24228958579788015},"bottomRight":{"x":1,"y":0.7912582030049035}},"flipX":false,"flipY":false,"altText":""},"parentId":"page:page","index":"aDa2zySG","typeName":"shape"},"asset:411255295":{"id":"asset:411255295","type":"image","typeName":"asset","props":{"name":"tldrawFile","src":"https://res.cloudinary.com/dfmr3wxuj/image/upload/v1780372072/xogidndoqbccnoeuygma.png","w":0,"h":0,"mimeType":"image/png","isAnimated":false,"fileSize":1401459},"meta":{}},"shape:aeffv7WeSV35wGh7KlSnR":{"x":507.52662224162657,"y":866.9317065779701,"rotation":0,"isLocked":false,"opacity":1,"meta":{},"id":"shape:aeffv7WeSV35wGh7KlSnR","type":"text","props":{"color":"black","size":"m","w":778.6015625,"font":"mono","textAlign":"start","autoSize":true,"scale":1,"richText":{"type":"doc","attrs":{"dir":"auto"},"content":[{"type":"paragraph","attrs":{"dir":"auto"},"content":[{"type":"text","text":"about me:"}]},{"type":"paragraph","attrs":{"dir":"auto"},"content":[{"type":"text","text":"i like raindrops on roses and whiskers on kittens,"}]},{"type":"paragraph","attrs":{"dir":"auto"},"content":[{"type":"text","text":"bright copper kettles "},{"type":"text","marks":[{"type":"italic"}],"text":"and "},{"type":"text","text":"warm woolen mittens."}]},{"type":"paragraph","attrs":{"dir":"auto"}},{"type":"paragraph","attrs":{"dir":"auto"},"content":[{"type":"text","text":"also wild geese that fly with the moon on their wings."},{"type":"hardBreak","attrs":{"dir":"auto"}}]}]}},"parentId":"page:page","index":"aidiMlhV","typeName":"shape"},"shape:W_oHm995eA3oQBt2ZdcSi":{"x":1299.7030342625544,"y":528.1868769509762,"rotation":0,"isLocked":false,"opacity":1,"meta":{},"id":"shape:W_oHm995eA3oQBt2ZdcSi","type":"draw","props":{"segments":[{"type":"free","path":"AAAAAAAAAAAAAAA/AAApPAAAKTwAAAAAAAAAAAAAAAAzPAAAMzwAAAAAAAApPAAAKTwAAAAAMzwzPAAAAAApPAAAKTwAAAAAMzwzPAAAKTwpPAAAMzwzPAAAKTwAAAAAMzwpPAAAKTwAAAAAMzwzPAAAKTwAAAAAMzwAAAAAAAApPAAALkAAAAAAQ0IAAAAAMzwAAAAALkAAAAAAKTwAAAAAMzwAAAAAKTwAAAAAMzwAAAAAKTwAAAAAMzwAAAAAKTwAAAAAAAAAAAAAMzwpvAAAKTwAAAAALkAzvAAAMzwAAAAAKTwAAAAAMzwAAAAALkAAAAAAKTwAAAAAKTwAAAAAMzwAAAAAKTwAAAAAAAApvAAAMzwAAAAAKTwAAAAAMzwAAAAAAAAzvAAAKTwpvAAAMzwAAAAAAAAzvAAAKTwAAAAAMzwpvAAAAAAzvAAAKTwAAAAAMzwAAAAAAAApvAAAKTwAAAAAAAAzvAAAMzwAAAAAAAApvAAAKTwAAAAAAAApvAAA"}],"color":"black","fill":"none","dash":"draw","size":"m","isComplete":true,"isClosed":false,"isPen":false,"scale":1,"scaleX":1,"scaleY":1},"parentId":"page:page","index":"aI7AnAyV","typeName":"shape"},"shape:Qw6QC8tPoi1PUO1324R8o":{"x":496.1974560511279,"y":504.9407616678302,"rotation":0,"isLocked":false,"opacity":1,"meta":{},"id":"shape:Qw6QC8tPoi1PUO1324R8o","type":"text","props":{"color":"black","size":"m","w":519.4000244140625,"font":"mono","textAlign":"start","autoSize":true,"scale":1,"richText":{"type":"doc","attrs":{"dir":"auto"},"content":[{"type":"paragraph","attrs":{"dir":"auto"},"content":[{"type":"text","text":"email: "},{"type":"text","marks":[{"type":"link","attrs":{"href":"mailto:mylesrhinehartdavis@gmail.com","target":"_blank","rel":"noopener noreferrer nofollow","class":null,"title":null}}],"text":"mylesrhinehartdavis@gmail.com"}]},{"type":"paragraph","attrs":{"dir":"auto"},"content":[{"type":"text","text":"phone: (509)-407-7551"}]}]}},"parentId":"page:page","index":"aE61lK9V","typeName":"shape"},"shape:CUHE2rjwAnSQmXozIrN9q":{"x":2717.7620637505556,"y":299.87868184495744,"rotation":0,"isLocked":false,"opacity":1,"meta":{},"id":"shape:CUHE2rjwAnSQmXozIrN9q","type":"text","props":{"color":"black","size":"m","w":404.20001220703125,"font":"mono","textAlign":"start","autoSize":true,"scale":1,"richText":{"type":"doc","attrs":{"dir":"auto"},"content":[{"type":"paragraph","attrs":{"dir":"auto"},"content":[{"type":"text","text":"For the homies interested, "}]},{"type":"paragraph","attrs":{"dir":"auto"},"content":[{"type":"text","text":"you can see how I made this "}]},{"type":"paragraph","attrs":{"dir":"auto"},"content":[{"type":"text","text":"on "},{"type":"text","marks":[{"type":"link","attrs":{"href":"https://github.com/mylesisbadatcoding/my1es.com2","target":"_blank","rel":"noopener noreferrer nofollow","class":null,"title":null}}],"text":"Github"},{"type":"text","text":"."}]},{"type":"paragraph","attrs":{"dir":"auto"}},{"type":"paragraph","attrs":{"dir":"auto"}}]}},"parentId":"page:page","index":"aWONZlBV","typeName":"shape"},"asset:-1982454247":{"id":"asset:-1982454247","type":"image","typeName":"asset","props":{"name":"tldrawFile","src":"https://res.cloudinary.com/dfmr3wxuj/image/upload/v1780372122/uqguggzfdbxuenmtcv6a.png","w":0,"h":0,"mimeType":"image/png","isAnimated":false,"fileSize":928473},"meta":{}},"shape:gc_ZSx3xAfWQZ6V6DiG2m":{"x":-1704.7048609781841,"y":1283.3615761938972,"rotation":0,"isLocked":false,"opacity":1,"meta":{},"id":"shape:gc_ZSx3xAfWQZ6V6DiG2m","type":"image","props":{"w":467.1809531662132,"h":350.3857148746599,"assetId":"asset:1191422016","playing":true,"url":"","crop":null,"flipX":false,"flipY":false,"altText":""},"parentId":"page:page","index":"aQsQA7tV","typeName":"shape"},"asset:-1018698235":{"id":"asset:-1018698235","type":"image","typeName":"asset","props":{"name":"IMG_0887.jpeg","src":"https://res.cloudinary.com/dfmr3wxuj/image/upload/v1780370019/kjbhjmq6inuea6eqohwe.jpg","w":0,"h":0,"mimeType":"image/jpeg","isAnimated":false,"fileSize":403981},"meta":{}},"asset:1581100442":{"id":"asset:1581100442","type":"image","typeName":"asset","props":{"name":"deer.jpg","src":"asset:1581100442","w":1125,"h":939,"fileSize":604920,"mimeType":"image/jpeg","isAnimated":false},"meta":{}},"asset:551803606":{"id":"asset:551803606","type":"image","typeName":"asset","props":{"name":"tldrawFile","src":"https://res.cloudinary.com/dfmr3wxuj/image/upload/v1780372555/wwgig6ispd26fxdelrrn.png","w":0,"h":0,"mimeType":"image/png","isAnimated":false,"fileSize":2652527},"meta":{}},"shape:ecoO1f4hrLGU8t664W8lD":{"x":811.7484113435216,"y":545.9496790700846,"rotation":0,"isLocked":false,"opacity":1,"meta":{},"id":"shape:ecoO1f4hrLGU8t664W8lD","type":"geo","props":{"w":480,"h":210.1999969482422,"geo":"rectangle","dash":"dashed","growY":0,"url":"","scale":1,"color":"black","labelColor":"black","fill":"none","size":"m","font":"mono","align":"start","verticalAlign":"middle","richText":{"type":"doc","attrs":{"dir":"auto"},"content":[{"type":"paragraph","attrs":{"dir":"auto"},"content":[{"type":"text","text":"This is my personal website that serves as a general representation of my mind; projects I'm working on, things I like, and whatever else I want on the internet forever."}]}]}},"parentId":"page:page","index":"aFrSqtUl","typeName":"shape"},"shape:8QpqOvuWB6dSjrlWzr6QN":{"x":1378.0127937575435,"y":-109.63101694490763,"rotation":0,"isLocked":false,"opacity":1,"meta":{},"id":"shape:8QpqOvuWB6dSjrlWzr6QN","type":"arrow","props":{"kind":"arc","elbowMidPoint":0.5,"dash":"dotted","size":"l","fill":"solid","color":"black","labelColor":"black","bend":-118.29869870937364,"start":{"x":1.1744563664199177,"y":3.523369099259412},"end":{"x":664.608739479816,"y":-642.2872167586587},"arrowheadStart":"none","arrowheadEnd":"arrow","richText":{"type":"doc","content":[{"type":"paragraph"}]},"labelPosition":0.5,"font":"mono","scale":1},"parentId":"page:page","index":"akmPGZkV","typeName":"shape"},"shape:atZ9Ssl6zrmVEBO7eNfgo":{"x":-1579.210524749306,"y":1250.1513063510176,"rotation":0,"isLocked":false,"opacity":1,"meta":{},"id":"shape:atZ9Ssl6zrmVEBO7eNfgo","type":"text","props":{"color":"black","size":"m","w":188.1999969482422,"font":"mono","textAlign":"start","autoSize":true,"scale":1,"richText":{"type":"doc","attrs":{"dir":"auto"},"content":[{"type":"paragraph","attrs":{"dir":"auto"},"content":[{"type":"text","text":"(nice sunset)"}]}]}},"parentId":"page:page","index":"aSkLX2IV","typeName":"shape"},"binding:lZc04HI7DPEOmil8AfXHp":{"meta":{},"id":"binding:lZc04HI7DPEOmil8AfXHp","type":"arrow","fromId":"shape:b48di09TcEoqPRLcLABp6","toId":"shape:ckjqCg1EjOv6ma89HMSiv","props":{"isPrecise":true,"isExact":false,"normalizedAnchor":{"x":0.4569244923456911,"y":0.19912597670869708},"snap":"none","terminal":"end"},"typeName":"binding"},"shape:nXdPT_YYYL7IDA72gJ7Hx":{"x":-940.3725442941427,"y":1487.062362700758,"rotation":0,"isLocked":false,"opacity":1,"meta":{},"id":"shape:nXdPT_YYYL7IDA72gJ7Hx","type":"image","props":{"w":719.31873451021,"h":394.52425096805996,"assetId":"asset:-1982454247","playing":true,"url":"","crop":{"topLeft":{"x":0.16697457449945904,"y":0.24321226537736346},"bottomRight":{"x":0.8667009699374065,"y":0.754916871042811}},"flipX":false,"flipY":false,"altText":""},"parentId":"page:page","index":"a0KIZ4oV","typeName":"shape"},"user:EsBwY7WD0WTiGap1GLM93":{"name":"","color":"#55B467","imageUrl":"","meta":{},"id":"user:EsBwY7WD0WTiGap1GLM93","typeName":"user"},"shape:WDT_sps2r623X4eQxbWY4":{"x":722.6724603085804,"y":718.5711386259956,"rotation":0,"isLocked":false,"opacity":1,"meta":{},"id":"shape:WDT_sps2r623X4eQxbWY4","type":"image","props":{"w":172.43384230496122,"h":172.43384230496122,"assetId":"asset:-1548671940","playing":true,"url":"","crop":null,"flipX":false,"flipY":false,"altText":""},"parentId":"page:page","index":"ahcJz4UO","typeName":"shape"},"asset:996018736":{"id":"asset:996018736","type":"image","typeName":"asset","props":{"name":"1000015476.png","src":"https://res.cloudinary.com/dfmr3wxuj/image/upload/v1780377189/zhyufpsovmvluorm1kvy.png","w":0,"h":0,"mimeType":"image/png","isAnimated":false,"fileSize":3337},"meta":{}},"shape:G70Txd04xE9hFEbfh3lny":{"x":1318.5107070945512,"y":470.7189877420966,"rotation":0,"isLocked":false,"opacity":1,"meta":{},"id":"shape:G70Txd04xE9hFEbfh3lny","type":"draw","props":{"segments":[{"type":"free","path":"AAAAAAAAAAAAAAA/AAAuRAAAAAAuQAAAAABDQgAAAAAuQAAAKbxIQgAAAABDQgAAAAAuRAAAAAAuQAAAAAAuQAAAAABIQgAAAABDQgAAAAAzPAAAAAApPAAAAAAzPAAAAAApPAAAKTwzPAAAAAApPAAAAAAzPAAAAAApPAAA"}],"color":"black","fill":"none","dash":"draw","size":"m","isComplete":true,"isClosed":false,"isPen":false,"scale":1,"scaleX":1,"scaleY":1},"parentId":"page:page","index":"aGCqtupV","typeName":"shape"},"asset:-1548671940":{"id":"asset:-1548671940","type":"image","typeName":"asset","props":{"name":"1000015472.png","src":"https://res.cloudinary.com/dfmr3wxuj/image/upload/v1780376932/ncqqkemujff2lwz0fnzy.png","w":0,"h":0,"mimeType":"image/png","isAnimated":false,"fileSize":263180},"meta":{}},"shape:8dkSljbf2Eh9yRc4Zxi-1":{"x":2315.530965545446,"y":48.42241934948436,"rotation":0,"isLocked":false,"opacity":1,"meta":{},"id":"shape:8dkSljbf2Eh9yRc4Zxi-1","type":"image","props":{"w":383.3361889404255,"h":511.23921696237676,"assetId":"asset:551803606","playing":true,"url":"","crop":null,"flipX":false,"flipY":false,"altText":""},"parentId":"page:page","index":"aXmX6SqV","typeName":"shape"},"shape:KB2V00tXmMj9DXoSW9e6D":{"x":-912.8051758881708,"y":1891.7020433436362,"rotation":0,"isLocked":false,"opacity":1,"meta":{},"id":"shape:KB2V00tXmMj9DXoSW9e6D","type":"text","props":{"color":"black","size":"m","w":793,"font":"mono","textAlign":"start","autoSize":true,"scale":1,"richText":{"type":"doc","attrs":{"dir":"auto"},"content":[{"type":"paragraph","attrs":{"dir":"auto"},"content":[{"type":"text","text":"I'll add more here later, but the house is coming along"}]}]}},"parentId":"page:page","index":"aUDkHKFV","typeName":"shape"},"shape:Em3kaE1z05iQKCVsYL-7x":{"x":1137.0270207071096,"y":153.72395760591053,"rotation":0,"isLocked":false,"opacity":1,"meta":{},"id":"shape:Em3kaE1z05iQKCVsYL-7x","type":"arrow","props":{"kind":"arc","elbowMidPoint":0.5,"dash":"draw","size":"m","fill":"none","color":"black","labelColor":"black","bend":0,"start":{"x":0,"y":0},"end":{"x":1156.4632205266562,"y":0},"arrowheadStart":"none","arrowheadEnd":"arrow","richText":{"type":"doc","content":[{"type":"paragraph"}]},"labelPosition":0.5,"font":"mono","scale":1},"parentId":"page:page","index":"aVokrhbV","typeName":"shape"},"shape:NBxiJ9-avM_Musi1Df0iZ":{"x":2612.603499052329,"y":405.2260510614768,"rotation":0,"isLocked":false,"opacity":1,"meta":{},"id":"shape:NBxiJ9-avM_Musi1Df0iZ","type":"note","props":{"color":"black","richText":{"type":"doc","attrs":{"dir":"auto"},"content":[{"type":"paragraph","attrs":{"dir":"auto"},"content":[{"type":"text","text":"Here we see Spencer with the craziest crib hand of his life."}]}]},"size":"m","font":"mono","align":"middle","verticalAlign":"middle","labelColor":"black","growY":0,"fontSizeAdjustment":1,"url":"","scale":1,"textFirstEditedBy":"yDUutpbDxf8eX50pO4LtA"},"parentId":"page:page","index":"aYEDEvSV","typeName":"shape"},"asset:-390063427":{"id":"asset:-390063427","type":"image","typeName":"asset","props":{"name":"Screenshot from 2026-01-08 21-02-21.png","src":"asset:-390063427","w":1920,"h":1200,"fileSize":670362,"mimeType":"image/png","isAnimated":false},"meta":{}},"shape:L0sQhf4FNgsEZ7nKpkzcH":{"x":688.320601543125,"y":126.32347697897904,"rotation":0,"isLocked":false,"opacity":1,"meta":{},"id":"shape:L0sQhf4FNgsEZ7nKpkzcH","type":"text","props":{"color":"black","size":"l","w":433,"font":"mono","textAlign":"start","autoSize":true,"scale":1,"richText":{"type":"doc","attrs":{"dir":"auto"},"content":[{"type":"paragraph","attrs":{"dir":"auto"},"content":[{"type":"text","text":"Welcome to my1es.com"}]}]}},"parentId":"page:page","index":"a1NcuyEV","typeName":"shape"},"shape:VMTqvph5NFpmRm8GfY1Gq":{"x":1024.948253269816,"y":-141.92857833194785,"rotation":0,"isLocked":false,"opacity":1,"meta":{},"id":"shape:VMTqvph5NFpmRm8GfY1Gq","type":"image","props":{"w":437.0441791592512,"h":291.3627861061675,"assetId":"asset:-1172752067","playing":true,"url":"","crop":null,"flipX":false,"flipY":false,"altText":""},"parentId":"page:page","index":"ajlS5N8V","typeName":"shape"},"asset:1426694325":{"id":"asset:1426694325","type":"image","typeName":"asset","props":{"name":"1000015023.jpg","src":"https://res.cloudinary.com/dfmr3wxuj/image/upload/v1780376476/ofbomeb9gw8lpvrm6hyn.jpg","w":0,"h":0,"mimeType":"image/jpeg","isAnimated":false,"fileSize":49205},"meta":{}},"shape:M3Tbj1zvSuEjIgNTfhII4":{"x":386.8126329257624,"y":580.7380010327295,"rotation":0,"isLocked":false,"opacity":1,"meta":{},"id":"shape:M3Tbj1zvSuEjIgNTfhII4","type":"note","props":{"color":"black","richText":{"type":"doc","attrs":{"dir":"auto"},"content":[{"type":"paragraph","attrs":{"dir":"auto"},"content":[{"type":"text","text":"this is an infinite canvas built on the tldraw sdk "}]}]},"size":"m","font":"mono","align":"middle","verticalAlign":"middle","labelColor":"black","growY":0,"fontSizeAdjustment":1,"url":"","scale":1,"textFirstEditedBy":"yDUutpbDxf8eX50pO4LtA"},"parentId":"page:page","index":"aKz4GxMl","typeName":"shape"},"shape:SLvEK66PwtqMxDKIwWbT4":{"x":1337.3183799265482,"y":471.7638584549853,"rotation":0,"isLocked":false,"opacity":1,"meta":{},"id":"shape:SLvEK66PwtqMxDKIwWbT4","type":"draw","props":{"segments":[{"type":"free","path":"AAAAAAAAAAAAAAA/AAAuQAAAAABDQgAAAAAuQAAAAAAuQAAAAABIQgAAAAAuRAAAAABDQgAAAABFRgAAAABIQgAAAAAuQAAAAAAuQAAAAAAuQAAAKTwpPAAAAAAzPAAA"}],"color":"black","fill":"none","dash":"draw","size":"m","isComplete":true,"isClosed":false,"isPen":false,"scale":1,"scaleX":1,"scaleY":1},"parentId":"page:page","index":"aHCBhVfV","typeName":"shape"},"page:page":{"meta":{},"id":"page:page","name":"Page 1","index":"a1","typeName":"page"},"document:document":{"gridSize":10,"name":"","meta":{},"id":"document:document","typeName":"document"},"asset:-1172752067":{"id":"asset:-1172752067","type":"image","typeName":"asset","props":{"name":"5d3e01cd-6b8d-4399-8ffc-0166f72b6712_removalai_preview.png","src":"https://res.cloudinary.com/dfmr3wxuj/image/upload/v1780421650/nqpmfois3zssopms6nki.png","w":0,"h":0,"mimeType":"image/png","isAnimated":false,"fileSize":159654},"meta":{}},"asset:339480878":{"id":"asset:339480878","type":"image","typeName":"asset","props":{"name":"1000015473.webp","src":"https://res.cloudinary.com/dfmr3wxuj/image/upload/v1780377137/ilbp3yj964qpyhvbmh6d.webp","w":0,"h":0,"mimeType":"image/webp","isAnimated":false,"fileSize":78130},"meta":{}},"asset:473953075":{"id":"asset:473953075","type":"image","typeName":"asset","props":{"name":"1000015477.png","src":"https://res.cloudinary.com/dfmr3wxuj/image/upload/v1780377094/eflirgkgl8soz5upqthv.png","w":0,"h":0,"mimeType":"image/png","isAnimated":false,"fileSize":13950},"meta":{}},"shape:b48di09TcEoqPRLcLABp6":{"x":247.3801530947988,"y":828.1018280698813,"rotation":0,"isLocked":false,"opacity":1,"meta":{},"id":"shape:b48di09TcEoqPRLcLABp6","type":"arrow","props":{"kind":"arc","elbowMidPoint":0.5,"dash":"draw","size":"xl","fill":"none","color":"black","labelColor":"black","bend":56.82999608980141,"start":{"x":-13.84653338689941,"y":-2.7693066773797455},"end":{"x":-335.5273260208854,"y":233.19000958111087},"arrowheadStart":"none","arrowheadEnd":"arrow","richText":{"type":"doc","content":[{"type":"paragraph"}]},"labelPosition":0.5,"font":"draw","scale":1},"parentId":"page:page","index":"aOrP5U1t","typeName":"shape"},"asset:-1566926773":{"id":"asset:-1566926773","type":"image","typeName":"asset","props":{"name":"tldrawFile","src":"https://res.cloudinary.com/dfmr3wxuj/image/upload/v1780371958/xtloxofqbm7zzhqoam1k.png","w":0,"h":0,"mimeType":"image/png","isAnimated":false,"fileSize":1235764},"meta":{}},"shape:QRbj2EBcrF6U-aDnRvZJY":{"x":596.8126329257624,"y":580.7380010327295,"rotation":0,"isLocked":false,"opacity":1,"meta":{},"id":"shape:QRbj2EBcrF6U-aDnRvZJY","type":"note","props":{"color":"black","richText":{"type":"doc","attrs":{"dir":"auto"},"content":[{"type":"paragraph","attrs":{"dir":"auto"},"content":[{"type":"text","text":"that means you can scroll anywhere to see more stuff"}]}]},"size":"m","font":"mono","align":"middle","verticalAlign":"middle","labelColor":"black","growY":10.199996948242188,"fontSizeAdjustment":1,"url":"","scale":1,"textFirstEditedBy":"yDUutpbDxf8eX50pO4LtA"},"parentId":"page:page","index":"aJkCnA8V","typeName":"shape"},"shape:AyJuOej0y8IzyAhkXSVQG":{"x":496.1230032606004,"y":860.8819933785225,"rotation":0,"isLocked":false,"opacity":0.75,"meta":{},"id":"shape:AyJuOej0y8IzyAhkXSVQG","type":"geo","props":{"w":800.3633569797612,"h":288.87962310064154,"geo":"rectangle","dash":"dotted","growY":0,"url":"","scale":1,"color":"yellow","labelColor":"black","fill":"solid","size":"m","font":"draw","align":"middle","verticalAlign":"middle","richText":{"type":"doc","attrs":{"dir":"auto"},"content":[{"type":"paragraph","attrs":{"dir":"auto"}}]}},"parentId":"page:page","index":"ZzXwe0aV","typeName":"shape"},"user:LuQO8SXfhDqkvmogyyDki":{"name":"","color":"#F2555A","imageUrl":"","meta":{},"id":"user:LuQO8SXfhDqkvmogyyDki","typeName":"user"}},"schema":{"schemaVersion":2,"sequences":{"com.tldraw.store":5,"com.tldraw.asset":1,"com.tldraw.camera":1,"com.tldraw.document":2,"com.tldraw.instance":26,"com.tldraw.instance_page_state":5,"com.tldraw.page":1,"com.tldraw.instance_presence":6,"com.tldraw.pointer":1,"com.tldraw.shape":4,"com.tldraw.user":1,"com.tldraw.asset.image":6,"com.tldraw.asset.video":5,"com.tldraw.asset.bookmark":2,"com.tldraw.shape.group":0,"com.tldraw.shape.text":4,"com.tldraw.shape.bookmark":2,"com.tldraw.shape.draw":4,"com.tldraw.shape.geo":11,"com.tldraw.shape.note":12,"com.tldraw.shape.line":5,"com.tldraw.shape.frame":1,"com.tldraw.shape.arrow":8,"com.tldraw.shape.highlight":3,"com.tldraw.shape.embed":4,"com.tldraw.shape.image":5,"com.tldraw.shape.video":4,"com.tldraw.binding.arrow":1}}},"session":{"version":0,"currentPageId":"page:page","exportBackground":true,"isFocusMode":false,"isDebugMode":false,"isToolLocked":false,"isGridMode":false,"pageStates":[{"pageId":"page:page","camera":{"x":430.6621317432249,"y":811.1527706405161,"z":0.3681855104293048},"selectedShapeIds":[],"focusedGroupId":null}]}}